ndl_mitb/__init__.py
ndl_mitb/lab1.py
ndl_mitb/lab10.py
ndl_mitb/lab11.py
ndl_mitb/lab12.py
ndl_mitb/lab2.py
ndl_mitb/lab3.py
ndl_mitb/lab4.py
ndl_mitb/lab5.py
ndl_mitb/lab6.py
ndl_mitb/lab7.py
ndl_mitb/lab8.py
ndl_mitb-0.5.0.dist-info/METADATA
ndl_mitb-0.5.0.dist-info/WHEEL
ndl_mitb-0.5.0.dist-info/top_level.txt
ndl_mitb-0.5.0.dist-info/RECORD
